{
  "micro_image_name": "micro_0045_XI.jpg",
  "text": "XI",
  "global_poly": [
    [
      2688,
      494
    ],
    [
      2739,
      501
    ],
    [
      2735,
      532
    ],
    [
      2683,
      525
    ]
  ],
  "micro_poly": [
    [
      75,
      40
    ],
    [
      126,
      47
    ],
    [
      122,
      78
    ],
    [
      70,
      71
    ]
  ],
  "source_split_image": "split_3_2100_0.jpg",
  "split_poly": [
    [
      588,
      494
    ],
    [
      639,
      501
    ],
    [
      635,
      532
    ],
    [
      583,
      525
    ]
  ],
  "color_presence": {
    "blue": false,
    "green": true,
    "yellow": true,
    "red": true,
    "white": true
  },
  "color_stats": {
    "blue": {
      "pixels": 8,
      "ratio": 0.00017771064264611146
    },
    "green": {
      "pixels": 492,
      "ratio": 0.010929204522735856
    },
    "yellow": {
      "pixels": 410,
      "ratio": 0.009107670435613212
    },
    "red": {
      "pixels": 487,
      "ratio": 0.010818135371082036
    },
    "white": {
      "pixels": 43594,
      "ratio": 0.968389719439323
    }
  },
  "color_valid_pixels": 45017,
  "re_ocr_text": "XI",
  "re_ocr_confidence": 1.0,
  "re_ocr_details": [
    {
      "text": "XI",
      "confidence": 1.0,
      "color_info": null,
      "matched_key": "XⅠ",
      "template_match_res": 0,
      "template_match_score": false,
      "black_pixel_count": 0,
      "black_radio": 0,
      "template_name": "color_detection",
      "color_centers_separate": {
        "red": [
          [
            218,
            74
          ]
        ],
        "yellow": [
          [
            188,
            70
          ],
          [
            196,
            73
          ],
          [
            199,
            78
          ],
          [
            201,
            81
          ]
        ],
        "green": [
          [
            242,
            74
          ]
        ]
      },
      "color_presence": {
        "blue": false,
        "green": true,
        "yellow": true,
        "red": true,
        "white": true
      },
      "color_stats": {
        "blue": {
          "pixels": 8,
          "ratio": 0.00017771064264611146
        },
        "green": {
          "pixels": 492,
          "ratio": 0.010929204522735856
        },
        "yellow": {
          "pixels": 410,
          "ratio": 0.009107670435613212
        },
        "red": {
          "pixels": 487,
          "ratio": 0.010818135371082036
        },
        "white": {
          "pixels": 43594,
          "ratio": 0.968389719439323
        }
      }
    }
  ],
  "matched_keys": [
    "XⅠ"
  ]
}