{
    "input_path": "splits/split_118_13300_2100.jpg",
    "page_index": null,
    "model_settings": {
        "use_doc_preprocessor": true,
        "use_textline_orientation": false
    },
    "doc_preprocessor_res": {
        "input_path": null,
        "page_index": null,
        "model_settings": {
            "use_doc_orientation_classify": false,
            "use_doc_unwarping": false
        },
        "angle": -1
    },
    "dt_polys": [
        [
            [
                34,
                18
            ],
            [
                220,
                18
            ],
            [
                220,
                83
            ],
            [
                34,
                83
            ]
        ],
        [
            [
                321,
                46
            ],
            [
                392,
                44
            ],
            [
                394,
                107
            ],
            [
                323,
                109
            ]
        ],
        [
            [
                35,
                256
            ],
            [
                219,
                256
            ],
            [
                219,
                318
            ],
            [
                35,
                318
            ]
        ],
        [
            [
                301,
                282
            ],
            [
                402,
                282
            ],
            [
                402,
                345
            ],
            [
                301,
                345
            ]
        ]
    ],
    "text_det_params": {
        "limit_side_len": 64,
        "limit_type": "min",
        "thresh": 0.3,
        "max_side_limit": 4000,
        "box_thresh": 0.6,
        "unclip_ratio": 1.5
    },
    "text_type": "general",
    "textline_orientation_angles": [
        -1,
        -1,
        -1,
        -1
    ],
    "text_rec_score_thresh": 0.0,
    "return_word_box": false,
    "rec_texts": [
        "2600-1",
        "9G",
        "2000-1",
        "10G"
    ],
    "rec_scores": [
        0.9977462887763977,
        0.9961134195327759,
        0.9983623027801514,
        0.9905611872673035
    ],
    "rec_polys": [
        [
            [
                34,
                18
            ],
            [
                220,
                18
            ],
            [
                220,
                83
            ],
            [
                34,
                83
            ]
        ],
        [
            [
                321,
                46
            ],
            [
                392,
                44
            ],
            [
                394,
                107
            ],
            [
                323,
                109
            ]
        ],
        [
            [
                35,
                256
            ],
            [
                219,
                256
            ],
            [
                219,
                318
            ],
            [
                35,
                318
            ]
        ],
        [
            [
                301,
                282
            ],
            [
                402,
                282
            ],
            [
                402,
                345
            ],
            [
                301,
                345
            ]
        ]
    ],
    "rec_boxes": [
        [
            34,
            18,
            220,
            83
        ],
        [
            321,
            44,
            394,
            109
        ],
        [
            35,
            256,
            219,
            318
        ],
        [
            301,
            282,
            402,
            345
        ]
    ]
}