{
    "input_path": "splits/split_78_8400_1400.jpg",
    "page_index": null,
    "model_settings": {
        "use_doc_preprocessor": true,
        "use_textline_orientation": false
    },
    "doc_preprocessor_res": {
        "input_path": null,
        "page_index": null,
        "model_settings": {
            "use_doc_orientation_classify": false,
            "use_doc_unwarping": false
        },
        "angle": -1
    },
    "dt_polys": [
        [
            [
                831,
                0
            ],
            [
                861,
                0
            ],
            [
                861,
                15
            ],
            [
                831,
                15
            ]
        ],
        [
            [
                800,
                242
            ],
            [
                867,
                242
            ],
            [
                867,
                298
            ],
            [
                800,
                298
            ]
        ],
        [
            [
                252,
                259
            ],
            [
                432,
                259
            ],
            [
                432,
                308
            ],
            [
                252,
                308
            ]
        ],
        [
            [
                474,
                397
            ],
            [
                655,
                399
            ],
            [
                655,
                450
            ],
            [
                474,
                447
            ]
        ],
        [
            [
                782,
                477
            ],
            [
                853,
                477
            ],
            [
                853,
                537
            ],
            [
                782,
                537
            ]
        ],
        [
            [
                211,
                604
            ],
            [
                309,
                604
            ],
            [
                309,
                663
            ],
            [
                211,
                663
            ]
        ],
        [
            [
                467,
                613
            ],
            [
                568,
                613
            ],
            [
                568,
                672
            ],
            [
                467,
                672
            ]
        ],
        [
            [
                924,
                610
            ],
            [
                987,
                610
            ],
            [
                987,
                663
            ],
            [
                924,
                663
            ]
        ],
        [
            [
                306,
                629
            ],
            [
                421,
                629
            ],
            [
                421,
                705
            ],
            [
                306,
                705
            ]
        ],
        [
            [
                0,
                647
            ],
            [
                77,
                641
            ],
            [
                81,
                702
            ],
            [
                0,
                708
            ]
        ],
        [
            [
                583,
                671
            ],
            [
                594,
                671
            ],
            [
                594,
                678
            ],
            [
                583,
                678
            ]
        ],
        [
            [
                780,
                712
            ],
            [
                847,
                712
            ],
            [
                847,
                779
            ],
            [
                780,
                779
            ]
        ],
        [
            [
                972,
                777
            ],
            [
                1000,
                777
            ],
            [
                1000,
                826
            ],
            [
                972,
                826
            ]
        ]
    ],
    "text_det_params": {
        "limit_side_len": 64,
        "limit_type": "min",
        "thresh": 0.3,
        "max_side_limit": 4000,
        "box_thresh": 0.6,
        "unclip_ratio": 1.5
    },
    "text_type": "general",
    "textline_orientation_angles": [
        -1,
        -1,
        -1,
        -1,
        -1,
        -1,
        -1,
        -1,
        -1,
        -1,
        -1,
        -1,
        -1
    ],
    "text_rec_score_thresh": 0.0,
    "return_word_box": false,
    "rec_texts": [
        "1",
        "85",
        "79-85DG",
        "69-87DG",
        "87",
        "D49",
        "646",
        "71",
        "Q0",
        "5WG",
        "",
        "75",
        "7"
    ],
    "rec_scores": [
        0.18063795566558838,
        0.9996998310089111,
        0.9967368841171265,
        0.9945816397666931,
        0.999495267868042,
        0.999224841594696,
        0.9988461136817932,
        0.9996490478515625,
        0.2918776869773865,
        0.9989795684814453,
        0.0,
        0.9958695769309998,
        0.9807703495025635
    ],
    "rec_polys": [
        [
            [
                831,
                0
            ],
            [
                861,
                0
            ],
            [
                861,
                15
            ],
            [
                831,
                15
            ]
        ],
        [
            [
                800,
                242
            ],
            [
                867,
                242
            ],
            [
                867,
                298
            ],
            [
                800,
                298
            ]
        ],
        [
            [
                252,
                259
            ],
            [
                432,
                259
            ],
            [
                432,
                308
            ],
            [
                252,
                308
            ]
        ],
        [
            [
                474,
                397
            ],
            [
                655,
                399
            ],
            [
                655,
                450
            ],
            [
                474,
                447
            ]
        ],
        [
            [
                782,
                477
            ],
            [
                853,
                477
            ],
            [
                853,
                537
            ],
            [
                782,
                537
            ]
        ],
        [
            [
                211,
                604
            ],
            [
                309,
                604
            ],
            [
                309,
                663
            ],
            [
                211,
                663
            ]
        ],
        [
            [
                467,
                613
            ],
            [
                568,
                613
            ],
            [
                568,
                672
            ],
            [
                467,
                672
            ]
        ],
        [
            [
                924,
                610
            ],
            [
                987,
                610
            ],
            [
                987,
                663
            ],
            [
                924,
                663
            ]
        ],
        [
            [
                306,
                629
            ],
            [
                421,
                629
            ],
            [
                421,
                705
            ],
            [
                306,
                705
            ]
        ],
        [
            [
                0,
                647
            ],
            [
                77,
                641
            ],
            [
                81,
                702
            ],
            [
                0,
                708
            ]
        ],
        [
            [
                583,
                671
            ],
            [
                594,
                671
            ],
            [
                594,
                678
            ],
            [
                583,
                678
            ]
        ],
        [
            [
                780,
                712
            ],
            [
                847,
                712
            ],
            [
                847,
                779
            ],
            [
                780,
                779
            ]
        ],
        [
            [
                972,
                777
            ],
            [
                1000,
                777
            ],
            [
                1000,
                826
            ],
            [
                972,
                826
            ]
        ]
    ],
    "rec_boxes": [
        [
            831,
            0,
            861,
            15
        ],
        [
            800,
            242,
            867,
            298
        ],
        [
            252,
            259,
            432,
            308
        ],
        [
            474,
            397,
            655,
            450
        ],
        [
            782,
            477,
            853,
            537
        ],
        [
            211,
            604,
            309,
            663
        ],
        [
            467,
            613,
            568,
            672
        ],
        [
            924,
            610,
            987,
            663
        ],
        [
            306,
            629,
            421,
            705
        ],
        [
            0,
            641,
            81,
            708
        ],
        [
            583,
            671,
            594,
            678
        ],
        [
            780,
            712,
            847,
            779
        ],
        [
            972,
            777,
            1000,
            826
        ]
    ]
}