{
    "input_path": "splits/split_58_9800_1400.jpg",
    "page_index": null,
    "model_settings": {
        "use_doc_preprocessor": true,
        "use_textline_orientation": false
    },
    "doc_preprocessor_res": {
        "input_path": null,
        "page_index": null,
        "model_settings": {
            "use_doc_orientation_classify": false,
            "use_doc_unwarping": false
        },
        "angle": -1
    },
    "dt_polys": [
        [
            [
                516,
                1
            ],
            [
                591,
                4
            ],
            [
                589,
                52
            ],
            [
                514,
                49
            ]
        ],
        [
            [
                642,
                0
            ],
            [
                782,
                0
            ],
            [
                782,
                44
            ],
            [
                642,
                44
            ]
        ],
        [
            [
                195,
                61
            ],
            [
                267,
                63
            ],
            [
                265,
                120
            ],
            [
                193,
                117
            ]
        ],
        [
            [
                750,
                53
            ],
            [
                865,
                62
            ],
            [
                861,
                124
            ],
            [
                746,
                116
            ]
        ],
        [
            [
                302,
                68
            ],
            [
                416,
                68
            ],
            [
                416,
                135
            ],
            [
                302,
                135
            ]
        ],
        [
            [
                838,
                62
            ],
            [
                959,
                74
            ],
            [
                953,
                139
            ],
            [
                832,
                127
            ]
        ],
        [
            [
                302,
                127
            ],
            [
                409,
                127
            ],
            [
                409,
                190
            ],
            [
                302,
                190
            ]
        ],
        [
            [
                174,
                234
            ],
            [
                356,
                234
            ],
            [
                356,
                280
            ],
            [
                174,
                280
            ]
        ],
        [
            [
                579,
                232
            ],
            [
                652,
                232
            ],
            [
                652,
                293
            ],
            [
                579,
                293
            ]
        ],
        [
            [
                181,
                304
            ],
            [
                280,
                304
            ],
            [
                280,
                363
            ],
            [
                181,
                363
            ]
        ],
        [
            [
                418,
                400
            ],
            [
                520,
                400
            ],
            [
                520,
                460
            ],
            [
                418,
                460
            ]
        ],
        [
            [
                678,
                464
            ],
            [
                754,
                464
            ],
            [
                754,
                522
            ],
            [
                678,
                522
            ]
        ],
        [
            [
                184,
                478
            ],
            [
                296,
                475
            ],
            [
                298,
                528
            ],
            [
                185,
                531
            ]
        ],
        [
            [
                795,
                469
            ],
            [
                980,
                469
            ],
            [
                980,
                519
            ],
            [
                795,
                519
            ]
        ],
        [
            [
                390,
                491
            ],
            [
                473,
                491
            ],
            [
                473,
                571
            ],
            [
                390,
                571
            ]
        ],
        [
            [
                0,
                546
            ],
            [
                64,
                546
            ],
            [
                64,
                605
            ],
            [
                0,
                605
            ]
        ],
        [
            [
                227,
                553
            ],
            [
                334,
                553
            ],
            [
                334,
                612
            ],
            [
                227,
                612
            ]
        ],
        [
            [
                386,
                565
            ],
            [
                485,
                562
            ],
            [
                486,
                623
            ],
            [
                387,
                625
            ]
        ],
        [
            [
                675,
                562
            ],
            [
                780,
                562
            ],
            [
                780,
                624
            ],
            [
                675,
                624
            ]
        ]
    ],
    "text_det_params": {
        "limit_side_len": 64,
        "limit_type": "min",
        "thresh": 0.3,
        "max_side_limit": 4000,
        "box_thresh": 0.6,
        "unclip_ratio": 1.5
    },
    "text_type": "general",
    "textline_orientation_angles": [
        -1,
        -1,
        -1,
        -1,
        -1,
        -1,
        -1,
        -1,
        -1,
        -1,
        -1,
        -1,
        -1,
        -1,
        -1,
        -1,
        -1,
        -1,
        -1
    ],
    "text_rec_score_thresh": 0.0,
    "return_word_box": false,
    "rec_texts": [
        "16",
        "16DG",
        "26",
        "723",
        "oa",
        "oa",
        "D26",
        "14-20DG",
        "20",
        "607",
        "663",
        "24",
        "22DG",
        "18-24DG",
        "①",
        "22",
        "613",
        "640",
        "673"
    ],
    "rec_scores": [
        0.9998989105224609,
        0.993745744228363,
        0.9995037913322449,
        0.9970285296440125,
        0.5606122612953186,
        0.37076371908187866,
        0.9976770281791687,
        0.9920383095741272,
        0.995718240737915,
        0.9984899163246155,
        0.9994885921478271,
        0.9997971057891846,
        0.9990375638008118,
        0.9982065558433533,
        0.9206223487854004,
        0.9996525049209595,
        0.9996588230133057,
        0.9986425042152405,
        0.9996659755706787
    ],
    "rec_polys": [
        [
            [
                516,
                1
            ],
            [
                591,
                4
            ],
            [
                589,
                52
            ],
            [
                514,
                49
            ]
        ],
        [
            [
                642,
                0
            ],
            [
                782,
                0
            ],
            [
                782,
                44
            ],
            [
                642,
                44
            ]
        ],
        [
            [
                195,
                61
            ],
            [
                267,
                63
            ],
            [
                265,
                120
            ],
            [
                193,
                117
            ]
        ],
        [
            [
                750,
                53
            ],
            [
                865,
                62
            ],
            [
                861,
                124
            ],
            [
                746,
                116
            ]
        ],
        [
            [
                302,
                68
            ],
            [
                416,
                68
            ],
            [
                416,
                135
            ],
            [
                302,
                135
            ]
        ],
        [
            [
                838,
                62
            ],
            [
                959,
                74
            ],
            [
                953,
                139
            ],
            [
                832,
                127
            ]
        ],
        [
            [
                302,
                127
            ],
            [
                409,
                127
            ],
            [
                409,
                190
            ],
            [
                302,
                190
            ]
        ],
        [
            [
                174,
                234
            ],
            [
                356,
                234
            ],
            [
                356,
                280
            ],
            [
                174,
                280
            ]
        ],
        [
            [
                579,
                232
            ],
            [
                652,
                232
            ],
            [
                652,
                293
            ],
            [
                579,
                293
            ]
        ],
        [
            [
                181,
                304
            ],
            [
                280,
                304
            ],
            [
                280,
                363
            ],
            [
                181,
                363
            ]
        ],
        [
            [
                418,
                400
            ],
            [
                520,
                400
            ],
            [
                520,
                460
            ],
            [
                418,
                460
            ]
        ],
        [
            [
                678,
                464
            ],
            [
                754,
                464
            ],
            [
                754,
                522
            ],
            [
                678,
                522
            ]
        ],
        [
            [
                184,
                478
            ],
            [
                296,
                475
            ],
            [
                298,
                528
            ],
            [
                185,
                531
            ]
        ],
        [
            [
                795,
                469
            ],
            [
                980,
                469
            ],
            [
                980,
                519
            ],
            [
                795,
                519
            ]
        ],
        [
            [
                390,
                491
            ],
            [
                473,
                491
            ],
            [
                473,
                571
            ],
            [
                390,
                571
            ]
        ],
        [
            [
                0,
                546
            ],
            [
                64,
                546
            ],
            [
                64,
                605
            ],
            [
                0,
                605
            ]
        ],
        [
            [
                227,
                553
            ],
            [
                334,
                553
            ],
            [
                334,
                612
            ],
            [
                227,
                612
            ]
        ],
        [
            [
                386,
                565
            ],
            [
                485,
                562
            ],
            [
                486,
                623
            ],
            [
                387,
                625
            ]
        ],
        [
            [
                675,
                562
            ],
            [
                780,
                562
            ],
            [
                780,
                624
            ],
            [
                675,
                624
            ]
        ]
    ],
    "rec_boxes": [
        [
            514,
            1,
            591,
            52
        ],
        [
            642,
            0,
            782,
            44
        ],
        [
            193,
            61,
            267,
            120
        ],
        [
            746,
            53,
            865,
            124
        ],
        [
            302,
            68,
            416,
            135
        ],
        [
            832,
            62,
            959,
            139
        ],
        [
            302,
            127,
            409,
            190
        ],
        [
            174,
            234,
            356,
            280
        ],
        [
            579,
            232,
            652,
            293
        ],
        [
            181,
            304,
            280,
            363
        ],
        [
            418,
            400,
            520,
            460
        ],
        [
            678,
            464,
            754,
            522
        ],
        [
            184,
            475,
            298,
            531
        ],
        [
            795,
            469,
            980,
            519
        ],
        [
            390,
            491,
            473,
            571
        ],
        [
            0,
            546,
            64,
            605
        ],
        [
            227,
            553,
            334,
            612
        ],
        [
            386,
            562,
            486,
            625
        ],
        [
            675,
            562,
            780,
            624
        ]
    ]
}