{
  "micro_image_name": "micro_0025_D4.jpg",
  "text": "D4",
  "global_poly": [
    [
      4863,
      1057
    ],
    [
      4896,
      1057
    ],
    [
      4896,
      1083
    ],
    [
      4863,
      1083
    ]
  ],
  "micro_poly": [
    [
      300,
      40
    ],
    [
      333,
      40
    ],
    [
      333,
      66
    ],
    [
      300,
      66
    ]
  ],
  "source_split_image": "split_14_4200_700.jpg",
  "split_poly": [
    [
      663,
      357
    ],
    [
      696,
      357
    ],
    [
      696,
      383
    ],
    [
      663,
      383
    ]
  ],
  "color_presence": {
    "blue": true,
    "green": false,
    "yellow": false,
    "red": false,
    "white": true
  },
  "color_stats": {
    "blue": {
      "pixels": 145,
      "ratio": 0.0022562474714467994
    },
    "green": {
      "pixels": 4,
      "ratio": 6.224130955715308e-05
    },
    "yellow": {
      "pixels": 3,
      "ratio": 4.668098216786481e-05
    },
    "red": {
      "pixels": 0,
      "ratio": 0.0
    },
    "white": {
      "pixels": 64117,
      "ratio": 0.9976815112189961
    }
  },
  "color_valid_pixels": 64266,
  "re_ocr_text": "D4",
  "re_ocr_confidence": 1.0,
  "re_ocr_details": [
    {
      "text": "D4",
      "confidence": 1.0,
      "color_info": null,
      "matched_key": "D4",
      "color_presence": {
        "blue": true,
        "green": false,
        "yellow": false,
        "red": false,
        "white": true
      },
      "color_stats": {
        "blue": {
          "pixels": 145,
          "ratio": 0.0022562474714467994
        },
        "green": {
          "pixels": 4,
          "ratio": 6.224130955715308e-05
        },
        "yellow": {
          "pixels": 3,
          "ratio": 4.668098216786481e-05
        },
        "red": {
          "pixels": 0,
          "ratio": 0.0
        },
        "white": {
          "pixels": 64117,
          "ratio": 0.9976815112189961
        }
      }
    }
  ],
  "matched_keys": [
    "D4"
  ]
}