{
  "micro_image_name": "micro_0126_D19.jpg",
  "text": "D19",
  "global_poly": [
    [
      6005,
      1743
    ],
    [
      6104,
      1740
    ],
    [
      6105,
      1796
    ],
    [
      6006,
      1799
    ]
  ],
  "micro_poly": [
    [
      249,
      43
    ],
    [
      348,
      40
    ],
    [
      349,
      96
    ],
    [
      250,
      99
    ]
  ],
  "source_split_image": "split_74_5600_1400.jpg",
  "split_poly": [
    [
      405,
      343
    ],
    [
      504,
      340
    ],
    [
      505,
      396
    ],
    [
      406,
      399
    ]
  ],
  "color_presence": {
    "blue": true,
    "green": false,
    "yellow": false,
    "red": false,
    "white": true
  },
  "color_stats": {
    "blue": {
      "pixels": 295,
      "ratio": 0.006340949637813555
    },
    "green": {
      "pixels": 3,
      "ratio": 6.448423360488361e-05
    },
    "yellow": {
      "pixels": 0,
      "ratio": 0.0
    },
    "red": {
      "pixels": 0,
      "ratio": 0.0
    },
    "white": {
      "pixels": 46225,
      "ratio": 0.9935945661285815
    }
  },
  "color_valid_pixels": 46523,
  "re_ocr_text": "D19",
  "re_ocr_confidence": 1.0,
  "re_ocr_details": [
    {
      "text": "D19",
      "confidence": 1.0,
      "color_info": null,
      "matched_key": "D19",
      "color_presence": {
        "blue": true,
        "green": false,
        "yellow": false,
        "red": false,
        "white": true
      },
      "color_stats": {
        "blue": {
          "pixels": 295,
          "ratio": 0.006340949637813555
        },
        "green": {
          "pixels": 3,
          "ratio": 6.448423360488361e-05
        },
        "yellow": {
          "pixels": 0,
          "ratio": 0.0
        },
        "red": {
          "pixels": 0,
          "ratio": 0.0
        },
        "white": {
          "pixels": 46225,
          "ratio": 0.9935945661285815
        }
      }
    }
  ],
  "matched_keys": [
    "D19"
  ]
}